setup.py
birdstest/_init_.py
birdstest.egg-info/PKG-INFO
birdstest.egg-info/SOURCES.txt
birdstest.egg-info/dependency_links.txt
birdstest.egg-info/top_level.txt