Metadata-Version: 1.1
Name: birdstest
Version: 0.0.2
Summary: birds atttributes and functions
Home-page: UNKNOWN
Author: xiaoyong
Author-email: xiaoyong.zhu@starfivetech.com
License: apache 3.0
Platform: UNKNOWN
Requires: numpy
Requires: matplotlib
